{
    "fields": [
        {
            "binding": null,
            "description": "The type of the FHIR resource.",
            "example": "{\n  \"resourceType\": \"QuestionnaireResponse\"\n}\n",
            "example2": null,
            "example3": null,
            "example4": null,
            "name": "resourceType",
            "note": "resourceType must be QuestionnaireResponse",
            "required": "Yes",
            "type": "<a target=\"_blank\" href=\"https://hl7.org/fhir/R4/datatypes.html#string\"><code>string</code></a>",
            "url": "https://hl7.org/fhir/r4/json.html#resources"
        },
        {
            "binding": null,
            "description": "The logical id of the resource.",
            "example": "{\n  \"id\": \"SH-12508041\"\n}\n",
            "example2": null,
            "example3": null,
            "example4": null,
            "name": "id",
            "note": null,
            "required": "Yes",
            "type": "<a target=\"_blank\" href=\"https://hl7.org/fhir/R4/datatypes.html#id\"><code>id</code></a>",
            "url": "https://www.hl7.org/fhir/r4/resource-definitions.html#Resource.id"
        },
        {
            "binding": null,
            "description": "The Questionnaire that defines and organizes the questions for which answers are being provided.",
            "example": "{\n  \"questionnaire\": \"https://fhir-ehr-code.cerner.com/r4/ec2458f2-1e24-41c8-b71b-0e701af7583d/Questionnaire/SH-12508041\"\n}\n",
            "example2": null,
            "example3": null,
            "example4": null,
            "name": "questionnaire",
            "note": null,
            "required": "Yes",
            "type": "canonical(<a target=\"_blank\" href=\"https://hl7.org/fhir/R4/questionnaire.html\"><code>Questionnaire</code></a>)",
            "url": "https://hl7.org/fhir/r4/questionnaireresponse-definitions.html#QuestionnaireResponse.questionnaire"
        },
        {
            "binding": null,
            "description": "The position of the questionnaire response within its overall lifecycle.",
            "example": "{\n  \"status\": \"in-progress\"\n}\n",
            "example2": null,
            "example3": null,
            "example4": null,
            "name": "status",
            "note": "Status must be 'in-progress'.",
            "required": "Yes",
            "type": "<a target=\"_blank\" href=\"https://hl7.org/fhir/R4/datatypes.html#code\"><code>code</code></a>",
            "url": "https://hl7.org/fhir/r4/questionnaireresponse-definitions.html#QuestionnaireResponse.status"
        },
        {
            "binding": null,
            "description": "The subject of the questionnaire response. This is the patient the answers apply to, but is not necessarily the source of information.",
            "example": "{\n  \"subject\": {\n    \"reference\": \"Patient/12508041\"\n  }\n}\n",
            "example2": null,
            "example3": null,
            "example4": null,
            "name": "subject",
            "note": null,
            "required": "Yes",
            "type": "<a target=\"_blank\" href=\"https://hl7.org/fhir/R4/references.html\"><code>Reference</code></a>",
            "url": "https://hl7.org/fhir/r4/questionnaireresponse-definitions.html#QuestionnaireResponse.subject"
        },
        {
            "binding": null,
            "description": "A group or question item from the original questionnaire for which answers are provided.",
            "example": "{\n  \"item\": [\n    {\n      \"id\": \"111\",\n      \"linkId\": \"93\",\n      \"extension\": [\n        {​​​​​​​​​​​​\n          \"url\": \"https://fhir-ehr.cerner.com/r4/StructureDefinition/note\",\n          \"valueAnnotation\": {​​​​​​​​​​​​​​​​​​​\n            \"text\": \"category/group comment\"\n          }​​​​​​​​​​​​​​​​​​​​​​​​​​\n        }​​​​​​​​​​​​​​​​​​​​​​​​​​\n      ],\n      \"item\": [\n        {\n          \"linkId\": \"93-123\",\n          \"extension\": [\n            {​​​​​​​​​​​​\n              \"url\": \"https://fhir-ehr.cerner.com/r4/StructureDefinition/choice-answer\",\n              \"valueBoolean\": true\n            }​​​​​​​​​​​​​​​​​​​​​​​​​​\n          ],\n          \"answer\": [\n            {\n              \"valuestring\": \"Answer text\"\n            }\n          ]\n        }\n      ] \n    }\n  ]\n}\n",
            "example2": null,
            "example3": null,
            "example4": null,
            "name": "item",
            "note": null,
            "required": "Yes",
            "type": "<code>List</code> <code>of</code> <a target=\"_blank\" href=\"https://hl7.org/fhir/R4/backboneelement.html\"><code>BackboneElement</code></a>",
            "url": "https://hl7.org/fhir/r4/questionnaireresponse-definitions.html#QuestionnaireResponse.item"
        },
        {
            "binding": null,
            "description": "Unique id for inter-element referencing.",
            "example": "{\n  \"id\": \"111\"\n}\n",
            "example2": null,
            "example3": null,
            "example4": null,
            "name": "item.id",
            "note": "If an item.id is returned on a read, it must be provided on an update.",
            "required": "No",
            "type": "<a target=\"_blank\" href=\"https://hl7.org/fhir/R4/datatypes.html#string\"><code>string</code></a>",
            "url": "https://hl7.org/fhir/R4/element-definitions.html#Element.id"
        },
        {
            "binding": null,
            "description": "The item from the Questionnaire that corresponds to this item in the QuestionnaireResponse resource.",
            "example": "{\n  \"linkId\": \"93\"\n}\n",
            "example2": null,
            "example3": null,
            "example4": null,
            "name": "item.linkId",
            "note": null,
            "required": "Yes",
            "type": "<a target=\"_blank\" href=\"https://hl7.org/fhir/R4/datatypes.html#string\"><code>string</code></a>",
            "url": "https://hl7.org/fhir/r4/questionnaireresponse-definitions.html#QuestionnaireResponse.item.linkId"
        },
        {
            "binding": null,
            "description": "Additional details about a given QuestionnaireResponse group item.",
            "example": "{\n  \"extension\": [\n    {​​​​​​​​​​​​\n      \"url\": \"https://fhir-ehr.cerner.com/r4/StructureDefinition/note\",\n      \"valueAnnotation\": {​​​​​​​​​​​​​​​​​​​\n        \"text\": \"category/group comment\"\n      }​​​​​​​​​​​​​​​​​​​​​​​​​​\n    }​​​​​​​​​​​​​​​​​​​​​​​​​​\n  ]\n}\n",
            "example2": null,
            "example3": null,
            "example4": null,
            "name": "item.extension",
            "note": "Only the 'note' extension is supported for this field. Notes can only be added, not replaced or deleted.",
            "required": "No",
            "type": "<a target=\"_blank\" href=\"https://hl7.org/fhir/R4/extensibility.html#Extension\"><code>Extension</code></a>",
            "url": "https://fhir-ehr.cerner.com/r4/StructureDefinition/note"
        },
        {
            "binding": null,
            "description": "Questions nested beneath a group.",
            "example": "{\n  \"item\": [\n    {\n      \"linkId\": \"93-123\",\n      \"extension\": [\n        {​​​​​​​​​​​​\n          \"url\": \"https://fhir-ehr.cerner.com/r4/StructureDefinition/choice-answer\",\n          \"valueBoolean\": true\n        }​​​​​​​​​​​​​​​​​​​​​​​​​​\n      ],\n      \"answer\": [\n        {\n          \"valuestring\": \"Answer text\"\n        }\n      ]\n    }\n  ]\n}\n",
            "example2": null,
            "example3": null,
            "example4": null,
            "name": "item.item",
            "note": null,
            "required": "No",
            "type": "<code>List</code> <code>of</code> <a target=\"_blank\" href=\"https://hl7.org/fhir/R4/backboneelement.html\"><code>BackboneElement</code></a>",
            "url": "https://hl7.org/fhir/r4/questionnaireresponse-definitions.html#QuestionnaireResponse.item.item"
        },
        {
            "binding": null,
            "description": "The item from the Questionnaire that corresponds to this item in the QuestionnaireResponse resource.",
            "example": "{\n  \"linkId\": \"93-123\"\n}\n",
            "example2": null,
            "example3": null,
            "example4": null,
            "name": "item.item.linkId",
            "note": null,
            "required": "Yes",
            "type": "<a target=\"_blank\" href=\"https://hl7.org/fhir/R4/datatypes.html#string\"><code>string</code></a>",
            "url": "https://hl7.org/fhir/r4/questionnaireresponse-definitions.html#QuestionnaireResponse.item.linkId"
        },
        {
            "binding": null,
            "description": "Whether the answers come from a list of options.",
            "example": "{\n  \"extension\": [\n    {​​​​​​​​​​​​\n      \"url\": \"https://fhir-ehr.cerner.com/r4/StructureDefinition/choice-answer\",\n      \"valueBoolean\": true\n    }​​​​​​​​​​​​​​​​​​​​​​​​​​\n  ]\n}\n",
            "example2": null,
            "example3": null,
            "example4": null,
            "name": "item.item.extension",
            "note": "Only the 'choice-answer' extension is supported for this field. Extension must be provided and true when answering a question of type choice or open choice.",
            "required": "No",
            "type": "<a target=\"_blank\" href=\"https://hl7.org/fhir/R4/extensibility.html#Extension\"><code>Extension</code></a>",
            "url": "https://fhir-ehr.cerner.com/r4/StructureDefinition/choice-answer"
        },
        {
            "binding": null,
            "description": "The respondent's answer(s) to the question.",
            "example": "{\n  \"answer\": [\n    {\n      \"valueString\": \"Answer text\"\n    }\n  ]\n}\n",
            "example2": "{\n  \"answer\": [\n    {\n      \"valueCoding\": {\n        \"system\": \"https://fhir.cerner.com/ec2458f2-1e24-41c8-b71b-0e701af7583d/nomenclature\",\n        \"code\": \"960439\"\n      }\n    }\n  ]\n}\n",
            "example3": "{\n  \"answer\": [\n    {\n      \"valueQuantity\": {\n        \"value\": 20\n      }\n    }\n  ]\n}\n",
            "example4": null,
            "name": "item.item.answer",
            "note": "Only answer value types of String, Quantity, and Coding are supported.",
            "required": "Yes",
            "type": "<a target=\"_blank\" href=\"https://hl7.org/fhir/R4/datatypes.html#string\"><code>string</code></a> | <a target=\"_blank\" href=\"https://hl7.org/fhir/R4/datatypes.html#Coding\"><code>Coding</code></a> | <a target=\"_blank\" href=\"https://hl7.org/fhir/R4/datatypes.html#Quantity\"><code>Quantity</code></a>",
            "url": "https://hl7.org/fhir/r4/questionnaireresponse-definitions.html#QuestionnaireResponse.item.answer"
        }
    ],
    "name": "QuestionnaireResponse",
    "options": null,
    "table_name": "update"
}
