{"table_name":"terminology","options":null,"name":"Device","fields":[{"name":"identifier","type":"<code>List</code> <code>of</code> <a target=\"_blank\" href=\"http://hl7.org/fhir/DSTU2/datatypes.html#Identifier\"><code>Identifier</code></a>","required":"No","description":"Identifier(s) from manufacturer, owner and others.","example":null,"example2":null,"example3":null,"example4":null,"note":null,"binding":null,"url":"http://hl7.org/fhir/DSTU2/device-definitions.html#Device.identifier"},{"name":"identifier.type","type":"<a target=\"_blank\" href=\"http://hl7.org/fhir/DSTU2/datatypes.html#CodeableConcept\"><code>CodeableConcept</code></a>","required":"No","description":"The type for the identifier that can be used to determine which identifier to use for a specific purpose.","example":null,"example2":null,"example3":null,"example4":null,"note":null,"binding":{"description":"The type used to determine which identifier to use for a specific purpose.","note":"Currently will return SNO code from the below system.","terminology":[{"display":"Identifier Type Codes","system":"http://hl7.org/fhir/identifier-type","info_link":"http://hl7.org/fhir/DSTU2/valueset-identifier-type.html"}]},"url":"http://hl7.org/fhir/dstu2/datatypes-definitions.html#Identifier.type"},{"name":"type","type":"<a target=\"_blank\" href=\"http://hl7.org/fhir/DSTU2/datatypes.html#CodeableConcept\"><code>CodeableConcept</code></a>","required":"Yes","description":"The specific kind of device.","example":null,"example2":null,"example3":null,"example4":null,"note":null,"binding":{"description":"The type of device.","terminology":[{"display":"FDA Product Code Classification","system":"urn:oid:2.16.840.1.113883.6.303","info_link":"https://www.fda.gov/MedicalDevices/DeviceRegulationandGuidance/Overview/ClassifyYourDevice/ucm051668.htm"}]},"url":"http://hl7.org/fhir/DSTU2/device-definitions.html#Device.type"}]}
